{
    "id": "a750210trig15a",
    "stepAnswer": [
        "\\(\\frac{(x-1)}{(y+2)}\\)"
    ],
    "problemType": "MultipleChoice",
    "stepTitle": "Utvärdera uttrycket, $$sin\\left(\\frac{\\pi}{12}\\right)$$ .",
    "stepBody": "Det kan vara användbart att ta fram en bild av enhetscirkeln som referens.",
    "answerType": "string",
    "variabilization": {},
    "choices": [
        "(sqrt(3)-1)/(2-sqrt(2)",
        "(sqrt(2)-1)/(3-sqrt(2)",
        "(sqrt(1)-1)/(3-sqrt(2)",
        "(sqrt(3)-1)/(1-sqrt(2)"
    ]
}